rest_framework_discovery/__init__.py
rest_framework_discovery/apps.py
rest_framework_discovery/introspect.py
rest_framework_discovery/settings.py
rest_framework_discovery/urls.py
rest_framework_discovery/views.py
djangorestframework_discovery-0.1.8.dist-info/LICENSE.md
djangorestframework_discovery-0.1.8.dist-info/METADATA
djangorestframework_discovery-0.1.8.dist-info/WHEEL
djangorestframework_discovery-0.1.8.dist-info/top_level.txt
djangorestframework_discovery-0.1.8.dist-info/RECORD
