Metadata-Version: 2.1
Name: djangorestframework-discovery
Version: 0.1.8
Summary: Create a queryable data source from an existing database.
Home-page: https://github.com/ztroop/django-rest-framework-discovery
Author: Zackary Troop
License: BSD
Platform: UNKNOWN
Classifier: Development Status :: 4 - Beta
Classifier: Environment :: Web Environment
Classifier: Framework :: Django
Classifier: Intended Audience :: Developers
Classifier: License :: OSI Approved :: BSD License
Classifier: Operating System :: OS Independent
Classifier: Programming Language :: Python
Classifier: Topic :: Internet :: WWW/HTTP
Requires-Dist: django (>=2.2.0)
Requires-Dist: djangorestframework (>=3.12.0)
